lambda_learner-0.1.0-py3.9-nspkg.pth
linkedin/learner/ds/ds_utils.py
linkedin/learner/ds/feature.py
linkedin/learner/ds/index_map.py
linkedin/learner/ds/indexed_dataset.py
linkedin/learner/ds/indexed_model.py
linkedin/learner/ds/record.py
linkedin/learner/ds/representation_utils.py
linkedin/learner/ds/types.py
linkedin/learner/prediction/evaluator.py
linkedin/learner/prediction/hessian_type.py
linkedin/learner/prediction/linear_scorer.py
linkedin/learner/prediction/trainer.py
linkedin/learner/prediction/trainer_lbgfs.py
linkedin/learner/prediction/trainer_logistic_loss_with_l2.py
linkedin/learner/prediction/trainer_sequential_bayesian_logistic_loss_with_l2.py
linkedin/learner/prediction/trainer_square_loss_with_l2.py
linkedin/learner/utils/functions.py
linkedin/learner/utils/singleton.py
lambda_learner-0.1.0.dist-info/LICENSE
lambda_learner-0.1.0.dist-info/METADATA
lambda_learner-0.1.0.dist-info/NOTICE
lambda_learner-0.1.0.dist-info/WHEEL
lambda_learner-0.1.0.dist-info/namespace_packages.txt
lambda_learner-0.1.0.dist-info/top_level.txt
lambda_learner-0.1.0.dist-info/RECORD
