Metadata-Version: 2.1
Name: lambda-learner
Version: 0.1.0
Summary: UNKNOWN
Home-page: https://github.com/linkedin/lambda-learner
License: BSD-2-CLAUSE
Project-URL: Documentation, https://github.com/linkedin/lambda-learner/blob/main/README.md
Project-URL: Source, https://github.com/linkedin/lambda-learner
Project-URL: Tracker, https://github.com/linkedin/lambda-learner/issues
Keywords: lambda-learner incremental training
Platform: UNKNOWN
Classifier: Programming Language :: Python :: 3
Classifier: Intended Audience :: Science/Research
Classifier: Intended Audience :: Developers
Classifier: License :: OSI Approved
Requires-Python: >=3.6
Requires-Dist: numpy (>=1.19.4)
Requires-Dist: scipy (>=1.5.4)
Requires-Dist: scikit-learn (>=0.24.0)
Requires-Dist: typing-extensions (>=3.7.4)
